zelepy/__init__.py
zelepy/configs.py
zelepy/events.py
zelepy/helpers.py
zelepy/_internal/__init__.py
zelepy/_internal/_windows_utils.py
zelepy/_internal/_zelesis_utils.py
zelepy-0.0.5.dist-info/licenses/LICENSE
zelepy-0.0.5.dist-info/METADATA
zelepy-0.0.5.dist-info/WHEEL
zelepy-0.0.5.dist-info/top_level.txt
zelepy-0.0.5.dist-info/RECORD
