Metadata-Version: 2.4
Name: zelepy
Version: 0.0.5
Summary: Zelesis Neo API Python Bindings
Author: MrCoolGuy640
License-Expression: MIT
Keywords: zelesis,zelesis neo
Requires-Python: >=3.8
License-File: LICENSE
Requires-Dist: configobj>=5.0.0
Requires-Dist: zhmiscellanygsudo
Requires-Dist: Pillow>=9.0.0
Dynamic: license-file
